show_gpu_usage/__init__.py
show_gpu_usage/show_gpu_usage.py
show_gpu_usage-0.2.dist-info/METADATA
show_gpu_usage-0.2.dist-info/WHEEL
show_gpu_usage-0.2.dist-info/top_level.txt
show_gpu_usage-0.2.dist-info/RECORD
